adala/__init__.py
adala_pk_test-0.0.1.post0.dist-info/METADATA
adala_pk_test-0.0.1.post0.dist-info/WHEEL
adala_pk_test-0.0.1.post0.dist-info/RECORD
