Metadata-Version: 2.1
Name: adala-pk-test
Version: 0.0.1.post0
Summary: ADALA: Automated Data Labeling Agent
Author-Email: Human Signal <hello@humansignal.com>
Requires-Python: >=3.8.8
Requires-Dist: pandas
Requires-Dist: openai
Requires-Dist: guidance
Requires-Dist: pydantic>=2
Requires-Dist: rich>=13
Requires-Dist: redis-om
